outleap/__init__.py
outleap/api_wrappers.py
outleap/bridge.py
outleap/client.py
outleap/protocol.py
outleap/qt_helpers.py
outleap/ui_elems.py
outleap/utils.py
outleap/version.py
outleap/scripts/__init__.py
outleap/scripts/agent.py
outleap/scripts/inspector.py
outleap/scripts/repl.py
outleap/scripts/ui/inspector.ui
outleap-0.8.1.dist-info/licenses/COPYING
outleap-0.8.1.dist-info/METADATA
outleap-0.8.1.dist-info/WHEEL
outleap-0.8.1.dist-info/entry_points.txt
outleap-0.8.1.dist-info/top_level.txt
outleap-0.8.1.dist-info/RECORD
