Metadata-Version: 2.4
Name: outleap
Version: 0.8.1
Summary: Tools for using asyncio to control a Second Life viewer over the LEAP protocol
Author-email: Salad Dais <83434023+SaladDais@users.noreply.github.com>
License: MIT License
Project-URL: homepage, https://github.com/SaladDais/outleap
Project-URL: repository, https://github.com/SaladDais/outleap
Classifier: Development Status :: 4 - Beta
Classifier: Intended Audience :: Developers
Classifier: License :: OSI Approved :: MIT License
Classifier: Natural Language :: English
Classifier: Operating System :: OS Independent
Classifier: Programming Language :: Python :: 3
Classifier: Programming Language :: Python :: 3.8
Classifier: Programming Language :: Python :: 3.9
Classifier: Programming Language :: Python :: 3.10
Classifier: Programming Language :: Python :: 3.11
Classifier: Programming Language :: Python :: 3.12
Requires-Python: >=3.8
License-File: COPYING
Requires-Dist: llsd==1.0.0
Requires-Dist: setuptools
Provides-Extra: tools
Requires-Dist: ptpython<4,>=3; extra == "tools"
Requires-Dist: qasync; extra == "tools"
Requires-Dist: pyside6-essentials; extra == "tools"
Dynamic: license-file
